README.md
README_dev.md
configuration.py
dpc.py
dpc_test.py
environment.yml
requirements.txt
setup.py
datasets/Nov09JnyExport.csv
datasets/adult.csv
datasets/mnist_9.csv
datasets/simple_digits.csv
dpcgeneration/__init__.py
dpcgeneration/baysennetwork.py
dpcgeneration/copula.py
dpcgeneration/dpcopula.py
dpcgeneration/laplacenoise.py
dpcgeneration/nearest_correlation.py
dpcgeneration/privparams.py
dpcgeneration/utils.py
dpcgeneration.egg-info/PKG-INFO
dpcgeneration.egg-info/SOURCES.txt
dpcgeneration.egg-info/dependency_links.txt
dpcgeneration.egg-info/requires.txt
dpcgeneration.egg-info/top_level.txt
out/mnist0-oneway0.png
out/mnist0-twoway0.png
tests/__init__.py
tests/dpcgeneration_tests.py
tutorials/Simpledigits.ipynb
tutorials/adult_tuto.ipynb
tutorials/mnist_tuto.ipynb