Metadata-Version: 2.1
Name: dpcgeneration
Version: 0.1.5
Summary: dpc demo library
Home-page: https://bitbucket.csiro.au/projects/ISPGROUP/repos/dpc_generation/
Author: Sirine Mrabet
Author-email: mar003@csiro.au
License: MIT
Platform: UNKNOWN
Classifier: Intended Audience :: Developers
Classifier: License :: OSI Approved :: MIT License
Classifier: Programming Language :: Python
Classifier: Programming Language :: Python :: 3
Classifier: Programming Language :: Python :: 3.6
Classifier: Operating System :: OS Independent
